coaiapy/__init__.py
coaiapy/coaiacli.py
coaiapy/coaiamodule.py
coaiapy/cofuse.py
coaiapy/cogh.py
coaiapy/environment.py
coaiapy/mobile_template.py
coaiapy/pipeline.py
coaiapy/syntation.py
coaiapy/test_cli_fetch.py
coaiapy-0.4.5.dist-info/licenses/LICENSE
coaiapy-0.4.5.dist-info/METADATA
coaiapy-0.4.5.dist-info/WHEEL
coaiapy-0.4.5.dist-info/entry_points.txt
coaiapy-0.4.5.dist-info/top_level.txt
coaiapy-0.4.5.dist-info/RECORD
