Metadata-Version: 2.4
Name: coaiapy
Version: 0.4.5
Summary: A Python package for audio transcription, synthesis, and tagging using Boto3.
Home-page: https://github.com/jgwill/coaiapy
Author: Jean GUillaume ISabelle
Author-email: Jean GUillaume ISabelle <jgi@jgwill.com>
License: Creative Commons Legal Code
Classifier: Programming Language :: Python :: 3
Classifier: License :: OSI Approved :: MIT License
Classifier: Operating System :: OS Independent
Requires-Python: >=3.6
License-File: LICENSE
Requires-Dist: boto3<=1.26.137
Requires-Dist: mutagen<=1.45.1
Requires-Dist: certifi
Requires-Dist: charset-normalizer<3.1
Requires-Dist: chardet<4.0,>=3.0.2
Requires-Dist: idna
Requires-Dist: urllib3<2.0,>=1.21.1
Requires-Dist: redis<=4.3.6
Requires-Dist: requests<2.29.0,>=2.22.0
Requires-Dist: markdown
Requires-Dist: PyYAML
Dynamic: author
Dynamic: home-page
Dynamic: license-file
Dynamic: requires-python
